_jupytermoon/__init__.py
jupyterflow/__init__.py
jupyterflow/config_loader.py
jupyterflow/driver.py
jupyterflow/k8s_client.py
jupyterflow/printer.py
jupyterflow/render.py
jupyterflow/runtime.py
jupyterflow/utils.py
jupyterflow/workflow.py
jupyterflow/templates/cronworkflow.yaml
jupyterflow/templates/jupyterflow.yaml
jupyterflow/templates/workflow.yaml
jupyterflow-0.0.4.data/scripts/jupyterflow
jupyterflow-0.0.4.data/scripts/jupytermoon
jupytermoon/__init__.py
jupytermoon/driver.py
jupytermoon/templates/workflow.yaml
jupytermoon_/__init__.py
jupyterflow-0.0.4.dist-info/LICENSE
jupyterflow-0.0.4.dist-info/METADATA
jupyterflow-0.0.4.dist-info/WHEEL
jupyterflow-0.0.4.dist-info/top_level.txt
jupyterflow-0.0.4.dist-info/RECORD
