Metadata-Version: 2.1
Name: jupyterflow
Version: 0.0.4
Summary: Run your workflow on JupyterHub
Home-page: https://github.com/hongkunyoo/jupyterflow
Author: hongkunyoo
Author-email: hongkunyoo@gmail.com
License: BSD 3-Clause
Keywords: ctl,jupyterhub,pipeline,ML
Platform: UNKNOWN
Requires-Dist: escapism (>=1.0)
Requires-Dist: PyYAML (>=5.3)
Requires-Dist: kubernetes (>=12.0)
Requires-Dist: Jinja2 (>=2.11)
Requires-Dist: jinja2-ansible-filters (>=1.3)
Requires-Dist: click (>=7.1)
Requires-Dist: jsonpath-ng (>=1.5)
